std/__init__.py
std/py.typed
better_std-0.1.0.dist-info/METADATA
better_std-0.1.0.dist-info/WHEEL
better_std-0.1.0.dist-info/RECORD
