Metadata-Version: 2.4
Name: better-std
Version: 0.1.0
Summary: Add your description here
Author-email: hhglory <hhglory@outlook.com>
Requires-Python: >=3.12
